AUTHORS
COPYING
MANIFEST.in
README
build.sh
ez_setup.py
gen-doc-api.sh
setup.cfg
setup.py
edje/__init__.py
edje/decorators.py
edje/edje.c_edje.c
edje/edje.c_edje.h
edje/edje.c_edje.pyx
edje/edje.c_edje_external.pxi
edje/edje.c_edje_message.pxi
edje/edje.c_edje_object.pxi
edje/edit/__init__.py
edje/edit/c_edit.c
edje/edit/c_edit.pyx
edje/edit/c_edit_object.pxi
edje/edit/c_edit_object_color_class.pxi
edje/edit/c_edit_object_group.pxi
edje/edit/c_edit_object_part.pxi
edje/edit/c_edit_object_programs.pxi
edje/edit/c_edit_object_state.pxi
edje/edit/c_edit_object_text_style.pxi
examples/01-swallow.edc
examples/01-swallow.py
examples/evas-demo/01-app_launcher/01-app_launcher.edc
examples/evas-demo/01-app_launcher/01-app_launcher.py
examples/evas-demo/01-app_launcher/audio_player.png
examples/evas-demo/01-app_launcher/background.jpeg
examples/evas-demo/01-app_launcher/image_viewer.png
examples/evas-demo/01-app_launcher/video_player.png
examples/evas-demo/01-app_launcher/web_browser.png
examples/evas-demo/02-vkbd/02-vkbd.edc
examples/evas-demo/02-vkbd/02-vkbd.py
examples/evas-demo/02-vkbd/background.png
examples/evas-demo/02-vkbd/backspace-selected.png
examples/evas-demo/02-vkbd/backspace.png
examples/evas-demo/02-vkbd/key-default-selected.png
examples/evas-demo/02-vkbd/key-default.png
examples/evas-demo/02-vkbd/key-special-selected.png
examples/evas-demo/02-vkbd/key-special.png
examples/evas-demo/02-vkbd/keyboard-background.png
examples/evas-demo/02-vkbd/shift-selected.png
examples/evas-demo/02-vkbd/shift.png
examples/evas-demo/03-kinetic_list/03-kinetic_list.edc
examples/evas-demo/03-kinetic_list/03-kinetic_list.py
examples/evas-demo/03-kinetic_list/background.png
examples/evas-demo/03-kinetic_list/listitem.png
examples/evas-demo/03-kinetic_list/thumb_1.jpg
examples/evas-demo/03-kinetic_list/thumb_2.jpg
examples/evas-demo/03-kinetic_list/thumb_3.jpg
examples/evas-demo/03-kinetic_list/thumb_4.jpg
examples/evas-demo/03-kinetic_list/thumb_5.jpg
python_edje.egg-info/PKG-INFO
python_edje.egg-info/SOURCES.txt
python_edje.egg-info/dependency_links.txt
python_edje.egg-info/not-zip-safe
python_edje.egg-info/requires.txt
python_edje.egg-info/top_level.txt
